jageocoder_dbcreator/__main__.py
jageocoder_dbcreator/convertor.py
jageocoder_dbcreator/data/aliases.json
jageocoder_dbcreator/data_manager.py
jageocoder_dbcreator/spatial.py
jageocoder_dbcreator-0.1.1.dist-info/LICENSE
jageocoder_dbcreator-0.1.1.dist-info/METADATA
jageocoder_dbcreator-0.1.1.dist-info/WHEEL
jageocoder_dbcreator-0.1.1.dist-info/entry_points.txt
jageocoder_dbcreator-0.1.1.dist-info/RECORD
