Metadata-Version: 2.1
Name: jageocoder-dbcreator
Version: 0.1.1
Summary: Address database file creator for Jageocoder.
License: MIT
Author: Takeshi Sagara
Author-email: sagara@info-proto.com
Requires-Python: >=3.10,<3.13
Classifier: Development Status :: 4 - Beta
Classifier: License :: OSI Approved :: MIT License
Classifier: Operating System :: MacOS :: MacOS X
Classifier: Operating System :: Microsoft :: Windows :: Windows 11
Classifier: Operating System :: POSIX :: Linux
Classifier: Programming Language :: Python :: 3
Classifier: Programming Language :: Python :: 3.10
Classifier: Programming Language :: Python :: 3.11
Classifier: Programming Language :: Python :: 3.12
Requires-Dist: docopt-ng (>=0.9.0,<0.10.0)
Requires-Dist: jageocoder (==2.1.9.dev3)
Requires-Dist: pyproj (>=3.7.1,<4.0.0)
Requires-Dist: shapely (>=2.1.0,<3.0.0)
Requires-Dist: tqdm (>=4.67.1,<5.0.0)
